ceresdb_client-1.0.0.dist-info/METADATA
ceresdb_client-1.0.0.dist-info/WHEEL
ceresdb_client-1.0.0.dist-info/license_files/LICENSE
ceresdb_client/__init__.py
ceresdb_client/__init__.pyi
ceresdb_client/py.typed
ceresdb_client/ceresdb_client.abi3.so
ceresdb_client-1.0.0.dist-info/RECORD
