Metadata-Version: 2.1
Name: ceresdb-client
Version: 1.0.0
License-File: LICENSE
Summary: The python client for ceresdb.
Keywords: CeresDB
Author: CeresDB Authors <ceresdbservice@gmail.com>
Author-email: CeresDB Authors <ceresdbservice@gmail.com>
Requires-Python: >=3.7
